ocr_compare-0.2.2.data/scripts/basic_usage.py
ocr_compare-0.2.2.data/scripts/gdai_example.py
ocr_compare-0.2.2.data/scripts/ocr_comparison.py
ocrtool/__init__.py
ocrtool/cached_ocr.py
ocrtool/ocr.py
ocrtool/canonical_ocr/__init__.py
ocrtool/canonical_ocr/ocr_schema.py
ocrtool/document_scanner/__init__.py
ocrtool/ocr_impls/__init__.py
ocrtool/ocr_impls/cached_ocr_executor.py
ocrtool/ocr_impls/ocr_executor.py
ocrtool/ocr_impls/ocr_factory.py
ocrtool/ocr_impls/gdai/__init__.py
ocrtool/ocr_impls/gdai/gdai_config.py
ocrtool/ocr_impls/gdai/gdai_convert.py
ocrtool/ocr_impls/gdai/gdai_executor.py
ocrtool/ocr_impls/gdai/gdai_layout_executor.py
ocrtool/ocr_impls/gdai/ocr_execution.py
ocrtool/ocr_impls/tesseract/__init__.py
ocrtool/ocr_impls/tesseract/tesseract_executor.py
ocrtool/page_limit/__init__.py
ocrtool/page_limit/exceptions.py
ocrtool/page_limit/limits.py
ocrtool/page_limit/page_count.py
ocrtool/page_limit/page_limit_handler.py
ocrtool/scan/__init__.py
ocrtool/scan/document_scanner.py
ocrtool/scan/scan-script.py
ocr_compare-0.2.2.dist-info/METADATA
ocr_compare-0.2.2.dist-info/WHEEL
ocr_compare-0.2.2.dist-info/top_level.txt
ocr_compare-0.2.2.dist-info/RECORD
